fx_doc/__init__.py
fx_doc/cli.py
fx_doc/doc_builder.py
fx_doc/doc_server.py
fx_doc/sphinx_theme/conf.py
fx_doc/sphinx_theme/sphinx_libfx_theme/basic_mode_links.html
fx_doc/sphinx_theme/sphinx_libfx_theme/basic_mode_toc.html
fx_doc/sphinx_theme/sphinx_libfx_theme/downloads.html
fx_doc/sphinx_theme/sphinx_libfx_theme/help.html
fx_doc/sphinx_theme/sphinx_libfx_theme/index.html
fx_doc/sphinx_theme/sphinx_libfx_theme/info.html
fx_doc/sphinx_theme/sphinx_libfx_theme/page.html
fx_doc/sphinx_theme/sphinx_libfx_theme/search.html
fx_doc/sphinx_theme/sphinx_libfx_theme/theme.conf
fx_doc/sphinx_theme/sphinx_libfx_theme/static/config.json
fx_doc/sphinx_theme/sphinx_libfx_theme/static/service-worker.js
fx_doc/sphinx_theme/sphinx_libfx_theme/static/css/main.css
fx_doc/sphinx_theme/sphinx_libfx_theme/static/fontawesome/css/fa-brands.css
fx_doc/sphinx_theme/sphinx_libfx_theme/static/fontawesome/css/fa-brands.min.css
fx_doc/sphinx_theme/sphinx_libfx_theme/static/fontawesome/css/fa-regular.css
fx_doc/sphinx_theme/sphinx_libfx_theme/static/fontawesome/css/fa-regular.min.css
fx_doc/sphinx_theme/sphinx_libfx_theme/static/fontawesome/css/fa-solid.css
fx_doc/sphinx_theme/sphinx_libfx_theme/static/fontawesome/css/fa-solid.min.css
fx_doc/sphinx_theme/sphinx_libfx_theme/static/fontawesome/css/fontawesome-all.css
fx_doc/sphinx_theme/sphinx_libfx_theme/static/fontawesome/css/fontawesome-all.min.css
fx_doc/sphinx_theme/sphinx_libfx_theme/static/fontawesome/css/fontawesome.css
fx_doc/sphinx_theme/sphinx_libfx_theme/static/fontawesome/css/fontawesome.min.css
fx_doc/sphinx_theme/sphinx_libfx_theme/static/fontawesome/webfonts/fa-brands-400.eot
fx_doc/sphinx_theme/sphinx_libfx_theme/static/fontawesome/webfonts/fa-brands-400.svg
fx_doc/sphinx_theme/sphinx_libfx_theme/static/fontawesome/webfonts/fa-brands-400.ttf
fx_doc/sphinx_theme/sphinx_libfx_theme/static/fontawesome/webfonts/fa-brands-400.woff
fx_doc-0.12.0.dist-info/METADATA
fx_doc-0.12.0.dist-info/RECORD
fx_doc-0.12.0.dist-info/WHEEL
fx_doc-0.12.0.dist-info/entry_points.txt
fx_doc-0.12.0.dist-info/top_level.txt
