Metadata-Version: 2.1
Name: fx-doc
Version: 0.12.0
Summary: Build reStructuredText to HTML, PDF and text
Home-page: https://github.com/kevin-leptons/fx-doc
Author: Kevin Leptons
Author-email: kevin.leptons@gmail.com
License: MIT
Keywords: build,document,reStructuredText,HTML,PDF,texta
Platform: UNKNOWN
Classifier: Programming Language :: Python :: 2.7
Classifier: Programming Language :: Python :: 3
Classifier: Programming Language :: Python :: 3.3
Classifier: Programming Language :: Python :: 3.4
Classifier: Programming Language :: Python :: 3.5
Requires-Dist: sphinx (==1.7.2)
Requires-Dist: click (==6.7)
Requires-Dist: flake8 (==3.5.0)
Requires-Dist: PyYAML (==3.12)
Requires-Dist: htmlmin (==0.1.12)
Requires-Dist: pathlib (==1.0.1)
Requires-Dist: jsmin (==2.2.2)
Requires-Dist: csscompressor (==0.9.5)
Requires-Dist: Pillow (==5.0.0)
Requires-Dist: Flask (==0.12.2)
Requires-Dist: gunicorn (==19.7.1)
